{"v":"5.8.0","fr":30,"ip":0,"op":120,"w":512,"h":512,"nm":"LOGO_SIERRAS","ddd":0,"assets":[],"fonts":{"list":[{"fName":"Montserrat-Bold","fFamily":"Montserrat","fStyle":"Bold","ascent":74.1989135742188}]},"layers":[{"ddd":0,"ind":1,"ty":4,"nm":"agua contornos","td":1,"sr":1,"ks":{"o":{"a":0,"k":100,"ix":11},"r":{"a":0,"k":0,"ix":10},"p":{"a":0,"k":[256.079,239.033,0],"ix":2,"l":2},"a":{"a":0,"k":[53.767,43.08,0],"ix":1,"l":2},"s":{"a":0,"k":[100,100,100],"ix":6,"l":2}},"ao":0,"shapes":[{"ty":"gr","it":[{"ind":0,"ty":"sh","ix":1,"ks":{"a":0,"k":{"i":[[-5.771,7.792],[1.072,-0.551],[2.15,-0.069],[1.882,1.927],[0.085,2.646],[-1.275,1.531],[-1.782,1.216],[-2.439,1.402],[-2.215,3.217],[0.179,5.623],[3.745,3.191],[5.127,-0.164],[3.506,-4.252],[3.234,-7.554],[0,0],[2.028,-3.873],[2.706,-3.398],[4.071,-2.117],[5.458,-0.175],[6.36,5.193],[-9.784,-5.099],[-11.027,0.341],[-8.587,4.507]],"o":[[-1.065,0.769],[-3.095,1.589],[-3.308,0.106],[-2.054,-2.087],[-0.075,-2.315],[1.105,-1.691],[1.297,-0.869],[3.564,-2.433],[2.215,-3.216],[-0.197,-6.119],[-3.91,-3.186],[-6.615,0.212],[-3.512,4.085],[0,0],[-3.086,7.053],[-2.028,3.873],[-2.871,3.403],[-4.077,1.951],[-8.553,0.273],[6.039,9.234],[9.785,5.099],[9.693,-0.323],[8.587,-4.506]],"v":[[51.948,16.463],[48.742,18.445],[40.875,20.932],[33.09,18.201],[29.882,11.102],[31.683,5.333],[36.014,0.972],[41.617,-2.434],[50.286,-10.908],[53.338,-24.167],[47.427,-38.133],[33.872,-42.666],[18.689,-35.972],[8.57,-18.512],[8.338,-18.008],[0.667,-1.62],[-6.434,9.286],[-16.847,17.565],[-31.149,20.755],[-53.517,13.373],[-29.384,35.233],[2.359,42.489],[30.132,35.15]],"c":true},"ix":2},"nm":"Trazado 1","mn":"ADBE Vector Shape - Group","hd":false},{"ty":"fl","c":{"a":0,"k":[0.102225599102,0,0.894000004787,1],"ix":4},"o":{"a":0,"k":100,"ix":5},"r":1,"bm":0,"nm":"Relleno 1","mn":"ADBE Vector Graphic - Fill","hd":false},{"ty":"tr","p":{"a":0,"k":[53.767,43.081],"ix":2},"a":{"a":0,"k":[0,0],"ix":1},"s":{"a":0,"k":[100,100],"ix":3},"r":{"a":0,"k":0,"ix":6},"o":{"a":0,"k":100,"ix":7},"sk":{"a":0,"k":0,"ix":4},"sa":{"a":0,"k":0,"ix":5},"nm":"Transformar"}],"nm":"Grupo 1","np":2,"cix":2,"bm":0,"ix":1,"mn":"ADBE Vector Group","hd":false}],"ip":2,"op":120,"st":3,"cp":true,"bm":0},{"ddd":0,"ind":2,"ty":4,"nm":"Capa de formas 1","tt":1,"sr":1,"ks":{"o":{"a":0,"k":100,"ix":11},"r":{"a":0,"k":0,"ix":10},"p":{"a":1,"k":[{"i":{"x":0.372,"y":0.176},"o":{"x":0.147,"y":0.101},"t":-7,"s":[256,256,0],"to":[0,-14.833,0],"ti":[0,14.833,0]},{"t":37,"s":[256,167,0]}],"ix":2,"l":2},"a":{"a":0,"k":[0,0,0],"ix":1,"l":2},"s":{"a":0,"k":[100,100,100],"ix":6,"l":2}},"ao":0,"shapes":[{"ty":"gr","it":[{"ind":0,"ty":"sh","ix":1,"ks":{"a":1,"k":[{"i":{"x":0.833,"y":0.833},"o":{"x":0.167,"y":0.167},"t":0,"s":[{"i":[[0,0],[0,0],[0,0],[0,0],[-12,-5.68],[-23.25,-11.656]],"o":[[0,0],[0,0],[0,0],[0,0],[12,5.68],[23.25,11.656]],"v":[[72.184,-36.863],[72.184,36.863],[-72.184,36.863],[-72.184,-36.863],[-28.868,-36.863],[19.132,-36.863]],"c":true}]},{"i":{"x":0.833,"y":0.833},"o":{"x":0.167,"y":0.167},"t":11,"s":[{"i":[[0,0],[0,0],[0,0],[0,0],[-11.5,-5.523],[-24.5,13.663]],"o":[[0,0],[0,0],[0,0],[0,0],[11.5,5.523],[24.5,-13.663]],"v":[[72.184,-36.863],[72.184,36.863],[-72.184,36.863],[-72.184,-36.863],[-28.868,-36.863],[19.132,-36.863]],"c":true}]},{"i":{"x":0.833,"y":0.833},"o":{"x":0.167,"y":0.167},"t":18,"s":[{"i":[[0,0],[0,0],[0,0],[0,0],[-11.5,-5.523],[-20,-11.693]],"o":[[0,0],[0,0],[0,0],[0,0],[32,15.985],[23,15.67]],"v":[[72.184,-36.863],[72.184,36.863],[-72.184,36.863],[-72.184,-36.863],[-28.868,-36.863],[19.132,-36.863]],"c":true}]},{"i":{"x":0.833,"y":0.833},"o":{"x":0.167,"y":0.167},"t":24,"s":[{"i":[[0,0],[0,0],[0,0],[0,0],[-11.5,-5.523],[-12,11.779]],"o":[[0,0],[0,0],[0,0],[0,0],[32,15.985],[22.5,-22.189]],"v":[[72.184,-36.863],[72.184,36.863],[-72.184,36.863],[-72.184,-36.863],[-28.868,-36.863],[19.132,-36.863]],"c":true}]},{"i":{"x":0.833,"y":0.833},"o":{"x":0.167,"y":0.167},"t":31,"s":[{"i":[[0,0],[0,0],[0,0],[0,0],[-11.5,-5.523],[-13.5,4.535]],"o":[[0,0],[0,0],[0,0],[0,0],[22.5,7.051],[30.5,-16.539]],"v":[[72.184,-36.863],[72.184,36.863],[-72.184,36.863],[-72.184,-36.863],[-28.868,-36.863],[19.132,-36.863]],"c":true}]},{"t":39,"s":[{"i":[[0,0],[0,0],[0,0],[0,0],[-11.5,-5.523],[-25,-2.954]],"o":[[0,0],[0,0],[0,0],[0,0],[30,18.119],[48,-2.325]],"v":[[72.184,-36.863],[72.184,36.863],[-72.184,36.863],[-72.184,-36.863],[-28.868,-36.863],[19.132,-36.863]],"c":true}]}],"ix":2},"nm":"Trazado 1","mn":"ADBE Vector Shape - Group","hd":false},{"ty":"fl","c":{"a":0,"k":[0,0.811764705882,0.894117647059,1],"ix":4},"o":{"a":0,"k":100,"ix":5},"r":1,"bm":0,"nm":"Relleno 1","mn":"ADBE Vector Graphic - Fill","hd":false},{"ty":"tr","p":{"a":0,"k":[0.868,85.797],"ix":2},"a":{"a":0,"k":[0,0],"ix":1},"s":{"a":0,"k":[100,158.97],"ix":3},"r":{"a":0,"k":0,"ix":6},"o":{"a":0,"k":100,"ix":7},"sk":{"a":0,"k":0,"ix":4},"sa":{"a":0,"k":0,"ix":5},"nm":"Transformar"}],"nm":"Rectángulo 1","np":3,"cix":2,"bm":0,"ix":1,"mn":"ADBE Vector Group","hd":false}],"ip":-1,"op":120,"st":0,"cp":true,"bm":0},{"ddd":0,"ind":3,"ty":4,"nm":"reflejo contornos","sr":1,"ks":{"o":{"a":0,"k":100,"ix":11},"r":{"a":0,"k":0,"ix":10},"p":{"a":0,"k":[278.5,163.342,0],"ix":2,"l":2},"a":{"a":0,"k":[21.828,14.366,0],"ix":1,"l":2},"s":{"a":0,"k":[100,100,100],"ix":6,"l":2}},"ao":0,"hasMask":true,"masksProperties":[{"inv":false,"mode":"a","pt":{"a":1,"k":[{"i":{"x":0.833,"y":0.833},"o":{"x":0.167,"y":0.167},"t":42,"s":[{"i":[[0,0],[0,0],[0,0],[0,0]],"o":[[0,0],[0,0],[0,0],[0,0]],"v":[[41.878,0.253],[41.878,28.484],[85.034,28.484],[85.034,0.253]],"c":true}]},{"t":81,"s":[{"i":[[0,0],[0,0],[0,0],[0,0]],"o":[[0,0],[0,0],[0,0],[0,0]],"v":[[-3.121,0.254],[-3.121,28.485],[40.035,28.485],[40.035,0.254]],"c":true}]}],"ix":1},"o":{"a":0,"k":100,"ix":3},"x":{"a":0,"k":0,"ix":4},"f":{"a":0,"k":[0,0],"ix":2},"nm":"Máscara 1"}],"shapes":[{"ty":"gr","it":[{"ind":0,"ty":"sh","ix":1,"ks":{"a":0,"k":{"i":[[-4.702,-3.853],[3.358,3.363],[9.171,0.569],[-5.02,1.78],[0,0],[0,0]],"o":[[-2.404,-3.587],[-8.681,-8.691],[0.836,8.164],[0,0],[0,0],[3.415,0.607]],"v":[[21.578,14.115],[10.954,2.973],[-21.578,-14.115],[-15.3,10.506],[-5.031,-3.48],[8.281,8.555]],"c":true},"ix":2},"nm":"Trazado 1","mn":"ADBE Vector Shape - Group","hd":false},{"ty":"fl","c":{"a":0,"k":[0.647000002394,0.702000038297,0.560999971278,1],"ix":4},"o":{"a":0,"k":100,"ix":5},"r":1,"bm":0,"nm":"Relleno 1","mn":"ADBE Vector Graphic - Fill","hd":false},{"ty":"tr","p":{"a":0,"k":[21.828,14.366],"ix":2},"a":{"a":0,"k":[0,0],"ix":1},"s":{"a":0,"k":[100,100],"ix":3},"r":{"a":0,"k":0,"ix":6},"o":{"a":0,"k":100,"ix":7},"sk":{"a":0,"k":0,"ix":4},"sa":{"a":0,"k":0,"ix":5},"nm":"Transformar"}],"nm":"Grupo 1","np":2,"cix":2,"bm":0,"ix":1,"mn":"ADBE Vector Group","hd":false}],"ip":28,"op":120,"st":1,"cp":true,"bm":0},{"ddd":0,"ind":4,"ty":4,"nm":"sierra contornos","sr":1,"ks":{"o":{"a":0,"k":100,"ix":11},"r":{"a":0,"k":0,"ix":10},"p":{"a":0,"k":[255.92,193.727,0],"ix":2,"l":2},"a":{"a":0,"k":[53.768,47.954,0],"ix":1,"l":2},"s":{"a":0,"k":[100,100,100],"ix":6,"l":2}},"ao":0,"shapes":[{"ty":"gr","it":[{"ind":0,"ty":"sh","ix":1,"ks":{"a":0,"k":{"i":[[11.693,-15.787],[-1.072,0.551],[-2.15,0.069],[-1.883,-1.926],[-0.085,-2.646],[1.275,-1.531],[1.782,-1.216],[2.439,-1.403],[2.215,-3.217],[-0.18,-5.623],[-3.745,-3.192],[-5.127,0.164],[-3.506,4.251],[-3.234,7.554],[0,0],[-2.028,3.873],[-2.706,3.398],[-4.07,2.117],[-5.457,0.175],[-6.36,-5.193],[18.123,1.152]],"o":[[1.065,-0.769],[3.095,-1.589],[3.308,-0.106],[2.054,2.087],[0.075,2.316],[-1.105,1.691],[-1.297,0.869],[-3.564,2.432],[-2.215,3.216],[0.196,6.12],[3.909,3.186],[6.616,-0.212],[3.512,-4.086],[0,0],[3.086,-7.052],[2.029,-3.873],[2.871,-3.404],[4.077,-1.951],[8.553,-0.274],[-12.279,-18.778],[-14.867,0.428]],"v":[[-51.947,-11.59],[-48.742,-13.572],[-40.874,-16.059],[-33.089,-13.327],[-29.882,-6.228],[-31.682,-0.458],[-36.014,3.902],[-41.617,7.31],[-50.286,15.783],[-53.338,29.042],[-47.426,43.009],[-33.872,47.54],[-18.689,40.846],[-8.57,23.387],[-8.337,22.883],[-0.667,6.495],[6.434,-4.41],[16.848,-12.691],[31.15,-15.88],[53.518,-8.499],[-0.152,-47.704]],"c":true},"ix":2},"nm":"Trazado 1","mn":"ADBE Vector Shape - Group","hd":false},{"ty":"fl","c":{"a":0,"k":[0.438999998803,0.477999997606,0.380000005984,1],"ix":4},"o":{"a":0,"k":100,"ix":5},"r":1,"bm":0,"nm":"Relleno 1","mn":"ADBE Vector Graphic - Fill","hd":false},{"ty":"tr","p":{"a":0,"k":[53.767,47.955],"ix":2},"a":{"a":0,"k":[0,0],"ix":1},"s":{"a":0,"k":[100,100],"ix":3},"r":{"a":0,"k":0,"ix":6},"o":{"a":0,"k":100,"ix":7},"sk":{"a":0,"k":0,"ix":4},"sa":{"a":0,"k":0,"ix":5},"nm":"Transformar"}],"nm":"Grupo 1","np":2,"cix":2,"bm":0,"ix":1,"mn":"ADBE Vector Group","hd":false}],"ip":-4,"op":120,"st":0,"cp":true,"bm":0},{"ddd":0,"ind":5,"ty":4,"nm":"contenedor contornos","sr":1,"ks":{"o":{"a":0,"k":100,"ix":11},"r":{"a":0,"k":0,"ix":10},"p":{"a":0,"k":[256,215.5,0],"ix":2,"l":2},"a":{"a":0,"k":[77.75,77.75,0],"ix":1,"l":2},"s":{"a":0,"k":[100,100,100],"ix":6,"l":2}},"ao":0,"shapes":[{"ty":"gr","it":[{"ind":0,"ty":"sh","ix":1,"ks":{"a":0,"k":{"i":[[0,-42.802],[42.802,0],[0,42.802],[-42.802,0]],"o":[[0,42.802],[-42.802,0],[0,-42.802],[42.802,0]],"v":[[77.5,0],[0,77.5],[-77.5,0],[0,-77.5]],"c":true},"ix":2},"nm":"Trazado 1","mn":"ADBE Vector Shape - Group","hd":false},{"ty":"fl","c":{"a":0,"k":[0.961000031116,0.961000031116,0.961000031116,1],"ix":4},"o":{"a":0,"k":100,"ix":5},"r":1,"bm":0,"nm":"Relleno 1","mn":"ADBE Vector Graphic - Fill","hd":false},{"ty":"tr","p":{"a":0,"k":[77.75,77.75],"ix":2},"a":{"a":0,"k":[0,0],"ix":1},"s":{"a":0,"k":[100,100],"ix":3},"r":{"a":0,"k":0,"ix":6},"o":{"a":0,"k":100,"ix":7},"sk":{"a":0,"k":0,"ix":4},"sa":{"a":0,"k":0,"ix":5},"nm":"Transformar"}],"nm":"Grupo 1","np":2,"cix":2,"bm":0,"ix":1,"mn":"ADBE Vector Group","hd":false}],"ip":-1,"op":120,"st":0,"cp":true,"bm":0},{"ddd":0,"ind":6,"ty":5,"nm":"SIERRA DE LOS PADRES","sr":1,"ks":{"o":{"a":0,"k":100,"ix":11},"r":{"a":0,"k":0,"ix":10},"p":{"a":0,"k":[146,325,0],"ix":2,"l":2},"a":{"a":0,"k":[0,0,0],"ix":1,"l":2},"s":{"a":0,"k":[100,100,100],"ix":6,"l":2}},"ao":0,"hasMask":true,"masksProperties":[{"inv":false,"mode":"a","pt":{"a":0,"k":{"i":[[0,0],[0,0],[0,0],[0,0]],"o":[[0,0],[0,0],[0,0],[0,0]],"v":[[-3.496,-16.816],[-2.996,3.716],[231.58,3.216],[231.08,-17.316]],"c":true},"ix":1},"o":{"a":0,"k":100,"ix":3},"x":{"a":0,"k":0,"ix":4},"f":{"a":0,"k":[0,0],"ix":2},"nm":"Máscara 1"}],"t":{"d":{"k":[{"s":{"s":18,"f":"Montserrat-Bold","t":"SIERRA DE LOS PADRES","ca":0,"j":0,"tr":0,"lh":21.6000003814697,"ls":0,"fc":[0.565,0.616,0.498]},"t":0}]},"p":{},"m":{"g":1,"a":{"a":0,"k":[0,0],"ix":2}},"a":[{"nm":"Animación 1","s":{"t":0,"xe":{"a":0,"k":0,"ix":7},"ne":{"a":0,"k":0,"ix":8},"a":{"a":0,"k":100,"ix":4},"b":1,"rn":0,"sh":1,"sm":{"a":0,"k":100,"ix":6},"r":1},"a":{"p":{"a":1,"k":[{"i":{"x":0.833,"y":0.833},"o":{"x":0.167,"y":0.167},"t":76,"s":[0,16,0],"to":[0,-2.667,0],"ti":[0,2.667,0]},{"t":86,"s":[0,0,0]}],"ix":2}}}]},"ip":76,"op":120,"st":2,"cp":true,"bm":0},{"ddd":0,"ind":7,"ty":5,"nm":"COOPERATIVA DE SERVICIOS","sr":1,"ks":{"o":{"a":0,"k":100,"ix":11},"r":{"a":0,"k":0,"ix":10},"p":{"a":0,"k":[166,348,0],"ix":2,"l":2},"a":{"a":0,"k":[0,0,0],"ix":1,"l":2},"s":{"a":0,"k":[100,100,100],"ix":6,"l":2}},"ao":0,"hasMask":true,"masksProperties":[{"inv":false,"mode":"a","pt":{"a":0,"k":{"i":[[0,0],[0,0],[0,0],[0,0]],"o":[[0,0],[0,0],[0,0],[0,0]],"v":[[-10,-9.544],[-10,6.144],[196.341,6.144],[196.341,-9.544]],"c":true},"ix":1},"o":{"a":0,"k":100,"ix":3},"x":{"a":0,"k":0,"ix":4},"f":{"a":0,"k":[0,0],"ix":2},"nm":"Máscara 1"}],"t":{"d":{"k":[{"s":{"s":12,"f":"Montserrat-Bold","t":"COOPERATIVA DE SERVICIOS","ca":0,"j":0,"tr":0,"lh":14.4000005722046,"ls":0,"fc":[0.374,0.407,0.331]},"t":0}]},"p":{},"m":{"g":1,"a":{"a":0,"k":[0,0],"ix":2}},"a":[{"nm":"Animación 1","s":{"t":0,"xe":{"a":0,"k":0,"ix":7},"ne":{"a":0,"k":0,"ix":8},"a":{"a":0,"k":100,"ix":4},"b":1,"rn":0,"sh":1,"sm":{"a":0,"k":100,"ix":6},"r":1},"a":{"p":{"a":1,"k":[{"i":{"x":0.833,"y":0.833},"o":{"x":0.167,"y":0.167},"t":86,"s":[0,-10,0],"to":[0,1.667,0],"ti":[0,-1.667,0]},{"t":96,"s":[0,0,0]}],"ix":2}}}]},"ip":76,"op":120,"st":1,"cp":true,"bm":0},{"ddd":0,"ind":8,"ty":1,"nm":"Sólido Blanco 1","sr":1,"ks":{"o":{"a":0,"k":100,"ix":11},"r":{"a":0,"k":0,"ix":10},"p":{"a":0,"k":[256,256,0],"ix":2,"l":2},"a":{"a":0,"k":[256,256,0],"ix":1,"l":2},"s":{"a":0,"k":[100,100,100],"ix":6,"l":2}},"ao":0,"sw":512,"sh":512,"sc":"#ffffff","ip":0,"op":120,"st":0,"cp":false,"bm":0},{"ddd":0,"ind":9,"ty":1,"nm":"Sólido Gris pálido-Rojo 1","sr":1,"ks":{"o":{"a":0,"k":100,"ix":11},"r":{"a":0,"k":0,"ix":10},"p":{"a":0,"k":[256,256,0],"ix":2,"l":2},"a":{"a":0,"k":[256,256,0],"ix":1,"l":2},"s":{"a":0,"k":[100,100,100],"ix":6,"l":2}},"ao":0,"sw":512,"sh":512,"sc":"#494545","ip":-1,"op":122,"st":0,"cp":false,"bm":0}],"markers":[],"chars":[{"ch":"C","size":12,"style":"Bold","w":71.8,"data":{"shapes":[{"ty":"gr","it":[{"ind":0,"ty":"sh","ix":1,"ks":{"a":0,"k":{"i":[[-7.134,0],[-4.934,2.133],[-3.334,4.067],[0,0],[7,0],[3.4,1.9],[1.9,3.4],[0,4.334],[-1.9,3.4],[-3.4,1.9],[-4.334,0],[-4.734,-5.466],[0,0],[4.9,2.134],[6.066,0],[5.766,-3.1],[3.3,-5.5],[0,-6.933],[-3.3,-5.5],[-5.767,-3.1]],"o":[[6.066,0],[4.933,-2.133],[0,0],[-4.734,5.534],[-4.334,0],[-3.4,-1.9],[-1.9,-3.4],[0,-4.333],[1.9,-3.4],[3.4,-1.9],[7,0],[0,0],[-3.334,-4],[-4.9,-2.133],[-7.2,0],[-5.767,3.1],[-3.3,5.5],[0,6.934],[3.3,5.5],[5.766,3.1]],"v":[[41.8,1.2],[58.3,-2],[70.7,-11.3],[60.3,-20.9],[42.7,-12.6],[31.1,-15.45],[23.15,-23.4],[20.3,-35],[23.15,-46.6],[31.1,-54.55],[42.7,-57.4],[60.3,-49.2],[70.7,-58.8],[58.35,-68],[41.9,-71.2],[22.45,-66.55],[8.85,-53.65],[3.9,-35],[8.85,-16.35],[22.45,-3.45]],"c":true},"ix":2},"nm":"C","mn":"ADBE Vector Shape - Group","hd":false}],"nm":"C","np":3,"cix":2,"bm":0,"ix":1,"mn":"ADBE Vector Group","hd":false}]},"fFamily":"Montserrat"},{"ch":"O","size":12,"style":"Bold","w":84.4,"data":{"shapes":[{"ty":"gr","it":[{"ind":0,"ty":"sh","ix":1,"ks":{"a":0,"k":{"i":[[-7.267,0],[-5.8,3.134],[-3.334,5.5],[0,6.867],[3.333,5.5],[5.8,3.134],[7.266,0],[5.833,-3.133],[3.3,-5.5],[0,-6.866],[-3.3,-5.5],[-5.834,-3.133]],"o":[[7.266,0],[5.8,-3.133],[3.333,-5.5],[0,-6.866],[-3.334,-5.5],[-5.8,-3.133],[-7.267,0],[-5.834,3.134],[-3.3,5.5],[0,6.867],[3.3,5.5],[5.833,3.134]],"v":[[42.2,1.2],[61.8,-3.5],[75.5,-16.45],[80.5,-35],[75.5,-53.55],[61.8,-66.5],[42.2,-71.2],[22.55,-66.5],[8.85,-53.55],[3.9,-35],[8.85,-16.45],[22.55,-3.5]],"c":true},"ix":2},"nm":"O","mn":"ADBE Vector Shape - Group","hd":false},{"ind":1,"ty":"sh","ix":2,"ks":{"a":0,"k":{"i":[[4.133,0],[3.333,1.9],[1.9,3.4],[0,4.334],[-1.9,3.4],[-3.334,1.9],[-4.134,0],[-3.334,-1.9],[-1.9,-3.4],[0,-4.333],[1.9,-3.4],[3.333,-1.9]],"o":[[-4.134,0],[-3.334,-1.9],[-1.9,-3.4],[0,-4.333],[1.9,-3.4],[3.333,-1.9],[4.133,0],[3.333,1.9],[1.9,3.4],[0,4.334],[-1.9,3.4],[-3.334,1.9]],"v":[[42.2,-12.6],[31,-15.45],[23.15,-23.4],[20.3,-35],[23.15,-46.6],[31,-54.55],[42.2,-57.4],[53.4,-54.55],[61.25,-46.6],[64.1,-35],[61.25,-23.4],[53.4,-15.45]],"c":true},"ix":2},"nm":"O","mn":"ADBE Vector Shape - Group","hd":false}],"nm":"O","np":5,"cix":2,"bm":0,"ix":1,"mn":"ADBE Vector Group","hd":false}]},"fFamily":"Montserrat"},{"ch":"P","size":12,"style":"Bold","w":72.2,"data":{"shapes":[{"ty":"gr","it":[{"ind":0,"ty":"sh","ix":1,"ks":{"a":0,"k":{"i":[[6.2,0],[0,0],[0,0],[0,0],[0,0],[0,0],[-4.567,2.034],[-2.467,3.834],[0,5.134],[2.466,3.8],[4.566,2.067]],"o":[[0,0],[0,0],[0,0],[0,0],[0,0],[6.2,0],[4.566,-2.033],[2.466,-3.833],[0,-5.2],[-2.467,-3.8],[-4.567,-2.066]],"v":[[38.6,-70],[8.3,-70],[8.3,0],[24.5,0],[24.5,-19.3],[38.6,-19.3],[54.75,-22.35],[65.3,-31.15],[69,-44.6],[65.3,-58.1],[54.75,-66.9]],"c":true},"ix":2},"nm":"P","mn":"ADBE Vector Shape - Group","hd":false},{"ind":1,"ty":"sh","ix":2,"ks":{"a":0,"k":{"i":[[4.866,0],[0,0],[0,0],[0,0],[-2.534,-2.1],[0,-3.933],[2.533,-2.1]],"o":[[0,0],[0,0],[0,0],[4.866,0],[2.533,2.1],[0,3.867],[-2.534,2.1]],"v":[[37.7,-32.5],[24.5,-32.5],[24.5,-56.8],[37.7,-56.8],[48.8,-53.65],[52.6,-44.6],[48.8,-35.65]],"c":true},"ix":2},"nm":"P","mn":"ADBE Vector Shape - Group","hd":false}],"nm":"P","np":5,"cix":2,"bm":0,"ix":1,"mn":"ADBE Vector Group","hd":false}]},"fFamily":"Montserrat"},{"ch":"E","size":12,"style":"Bold","w":67.1,"data":{"shapes":[{"ty":"gr","it":[{"ind":0,"ty":"sh","ix":1,"ks":{"a":0,"k":{"i":[[0,0],[0,0],[0,0],[0,0],[0,0],[0,0],[0,0],[0,0],[0,0],[0,0],[0,0],[0,0]],"o":[[0,0],[0,0],[0,0],[0,0],[0,0],[0,0],[0,0],[0,0],[0,0],[0,0],[0,0],[0,0]],"v":[[24.4,-13],[24.4,-29.2],[56.9,-29.2],[56.9,-41.8],[24.4,-41.8],[24.4,-57],[61.2,-57],[61.2,-70],[8.3,-70],[8.3,0],[62.5,0],[62.5,-13]],"c":true},"ix":2},"nm":"E","mn":"ADBE Vector Shape - Group","hd":false}],"nm":"E","np":3,"cix":2,"bm":0,"ix":1,"mn":"ADBE Vector Group","hd":false}]},"fFamily":"Montserrat"},{"ch":"R","size":12,"style":"Bold","w":73.5,"data":{"shapes":[{"ty":"gr","it":[{"ind":0,"ty":"sh","ix":1,"ks":{"a":0,"k":{"i":[[0,0],[0,0],[-2.5,3.767],[0,5.2],[2.466,3.8],[4.566,2.067],[6.2,0],[0,0],[0,0],[0,0],[0,0],[0,0],[0,0],[0,0]],"o":[[0,0],[4.6,-2],[2.5,-3.766],[0,-5.2],[-2.467,-3.8],[-4.567,-2.066],[0,0],[0,0],[0,0],[0,0],[0,0],[0,0],[0,0],[0,0]],"v":[[70.3,0],[54.6,-22.5],[65.25,-31.15],[69,-44.6],[65.3,-58.1],[54.75,-66.9],[38.6,-70],[8.3,-70],[8.3,0],[24.5,0],[24.5,-19.5],[38.6,-19.5],[39.4,-19.5],[52.9,0]],"c":true},"ix":2},"nm":"R","mn":"ADBE Vector Shape - Group","hd":false},{"ind":1,"ty":"sh","ix":2,"ks":{"a":0,"k":{"i":[[0,-3.933],[2.533,-2.133],[4.866,0],[0,0],[0,0],[0,0],[-2.534,-2.1]],"o":[[0,3.867],[-2.534,2.134],[0,0],[0,0],[0,0],[4.866,0],[2.533,2.1]],"v":[[52.6,-44.6],[48.8,-35.6],[37.7,-32.4],[24.5,-32.4],[24.5,-56.8],[37.7,-56.8],[48.8,-53.65]],"c":true},"ix":2},"nm":"R","mn":"ADBE Vector Shape - Group","hd":false}],"nm":"R","np":5,"cix":2,"bm":0,"ix":1,"mn":"ADBE Vector Group","hd":false}]},"fFamily":"Montserrat"},{"ch":"A","size":12,"style":"Bold","w":78.9,"data":{"shapes":[{"ty":"gr","it":[{"ind":0,"ty":"sh","ix":1,"ks":{"a":0,"k":{"i":[[0,0],[0,0],[0,0],[0,0],[0,0],[0,0],[0,0],[0,0]],"o":[[0,0],[0,0],[0,0],[0,0],[0,0],[0,0],[0,0],[0,0]],"v":[[60.6,0],[77.6,0],[46.3,-70],[30.3,-70],[-0.9,0],[15.7,0],[21.9,-15],[54.4,-15]],"c":true},"ix":2},"nm":"A","mn":"ADBE Vector Shape - Group","hd":false},{"ind":1,"ty":"sh","ix":2,"ks":{"a":0,"k":{"i":[[0,0],[0,0],[0,0]],"o":[[0,0],[0,0],[0,0]],"v":[[27.1,-27.3],[38.2,-54.1],[49.3,-27.3]],"c":true},"ix":2},"nm":"A","mn":"ADBE Vector Shape - Group","hd":false}],"nm":"A","np":5,"cix":2,"bm":0,"ix":1,"mn":"ADBE Vector Group","hd":false}]},"fFamily":"Montserrat"},{"ch":"T","size":12,"style":"Bold","w":62.8,"data":{"shapes":[{"ty":"gr","it":[{"ind":0,"ty":"sh","ix":1,"ks":{"a":0,"k":{"i":[[0,0],[0,0],[0,0],[0,0],[0,0],[0,0],[0,0],[0,0]],"o":[[0,0],[0,0],[0,0],[0,0],[0,0],[0,0],[0,0],[0,0]],"v":[[22.8,0],[39,0],[39,-56.8],[61.4,-56.8],[61.4,-70],[0.4,-70],[0.4,-56.8],[22.8,-56.8]],"c":true},"ix":2},"nm":"T","mn":"ADBE Vector Shape - Group","hd":false}],"nm":"T","np":3,"cix":2,"bm":0,"ix":1,"mn":"ADBE Vector Group","hd":false}]},"fFamily":"Montserrat"},{"ch":"I","size":12,"style":"Bold","w":32.8,"data":{"shapes":[{"ty":"gr","it":[{"ind":0,"ty":"sh","ix":1,"ks":{"a":0,"k":{"i":[[0,0],[0,0],[0,0],[0,0]],"o":[[0,0],[0,0],[0,0],[0,0]],"v":[[8.3,0],[24.5,0],[24.5,-70],[8.3,-70]],"c":true},"ix":2},"nm":"I","mn":"ADBE Vector Shape - Group","hd":false}],"nm":"I","np":3,"cix":2,"bm":0,"ix":1,"mn":"ADBE Vector Group","hd":false}]},"fFamily":"Montserrat"},{"ch":"V","size":12,"style":"Bold","w":74.6,"data":{"shapes":[{"ty":"gr","it":[{"ind":0,"ty":"sh","ix":1,"ks":{"a":0,"k":{"i":[[0,0],[0,0],[0,0],[0,0],[0,0],[0,0],[0,0]],"o":[[0,0],[0,0],[0,0],[0,0],[0,0],[0,0],[0,0]],"v":[[59.5,-70],[37.9,-20],[16.6,-70],[-0.9,-70],[29.3,0],[45.3,0],[75.6,-70]],"c":true},"ix":2},"nm":"V","mn":"ADBE Vector Shape - Group","hd":false}],"nm":"V","np":3,"cix":2,"bm":0,"ix":1,"mn":"ADBE Vector Group","hd":false}]},"fFamily":"Montserrat"},{"ch":" ","size":12,"style":"Bold","w":28.3,"data":{},"fFamily":"Montserrat"},{"ch":"D","size":12,"style":"Bold","w":82.6,"data":{"shapes":[{"ty":"gr","it":[{"ind":0,"ty":"sh","ix":1,"ks":{"a":0,"k":{"i":[[0,0],[0,0],[-5.834,2.9],[-3.234,5.267],[0,7],[3.233,5.267],[5.833,2.9],[7.6,0],[0,0]],"o":[[0,0],[7.6,0],[5.833,-2.9],[3.233,-5.266],[0,-7],[-3.234,-5.266],[-5.834,-2.9],[0,0],[0,0]],"v":[[8.3,0],[40.1,0],[60.25,-4.35],[73.85,-16.6],[78.7,-35],[73.85,-53.4],[60.25,-65.65],[40.1,-70],[8.3,-70]],"c":true},"ix":2},"nm":"D","mn":"ADBE Vector Shape - Group","hd":false},{"ind":1,"ty":"sh","ix":2,"ks":{"a":0,"k":{"i":[[0,0],[0,0],[0,0],[-4.167,-3.9],[0,-6.666],[4.166,-3.9],[7,0]],"o":[[0,0],[0,0],[7,0],[4.166,3.9],[0,6.667],[-4.167,3.9],[0,0]],"v":[[24.5,-13.3],[24.5,-56.7],[39.3,-56.7],[56.05,-50.85],[62.3,-35],[56.05,-19.15],[39.3,-13.3]],"c":true},"ix":2},"nm":"D","mn":"ADBE Vector Shape - Group","hd":false}],"nm":"D","np":5,"cix":2,"bm":0,"ix":1,"mn":"ADBE Vector Group","hd":false}]},"fFamily":"Montserrat"},{"ch":"S","size":12,"style":"Bold","w":63.8,"data":{"shapes":[{"ty":"gr","it":[{"ind":0,"ty":"sh","ix":1,"ks":{"a":0,"k":{"i":[[-5.534,0],[-4.467,1.933],[-2.234,3.3],[0,4],[2.433,2.734],[3.4,1.267],[5.333,1.267],[2.5,1.167],[0,2.4],[-2.167,1.467],[-4.534,0],[-6.467,-3.666],[0,0],[4.266,1.067],[4.466,0],[4.433,-1.933],[2.2,-3.3],[0,-4.066],[-2.434,-2.8],[-3.4,-1.266],[-5.334,-1.266],[-2.034,-0.666],[-1.3,-1.1],[0,-1.666],[2.2,-1.366],[4.6,0],[4.133,1.334],[3,2.2],[0,0],[-5.167,-1.5]],"o":[[6.4,0],[4.466,-1.933],[2.233,-3.3],[0,-4.666],[-2.434,-2.733],[-3.4,-1.266],[-5.134,-1.133],[-2.5,-1.166],[0,-2.4],[2.166,-1.466],[6.466,0],[0,0],[-3.2,-2],[-4.267,-1.066],[-6.4,0],[-4.434,1.934],[-2.2,3.3],[0,4.667],[2.433,2.8],[3.4,1.267],[3.466,0.8],[2.033,0.667],[1.3,1.1],[0,2.267],[-2.2,1.367],[-4.134,0],[-4.134,-1.333],[0,0],[3.133,2.4],[5.166,1.5]],"v":[[31.3,1.2],[47.6,-1.7],[57.65,-9.55],[61,-20.5],[57.35,-31.6],[48.6,-37.6],[35.5,-41.4],[24.05,-44.85],[20.3,-50.2],[23.55,-56],[33.6,-58.2],[53,-52.7],[58,-65],[46.8,-69.6],[33.7,-71.2],[17.45,-68.3],[7.5,-60.45],[4.2,-49.4],[7.85,-38.2],[16.6,-32.1],[29.7,-28.3],[37.95,-26.1],[42.95,-23.45],[44.9,-19.3],[41.6,-13.85],[31.4,-11.8],[19,-13.8],[8.3,-19.1],[2.8,-6.9],[15.25,-1.05]],"c":true},"ix":2},"nm":"S","mn":"ADBE Vector Shape - Group","hd":false}],"nm":"S","np":3,"cix":2,"bm":0,"ix":1,"mn":"ADBE Vector Group","hd":false}]},"fFamily":"Montserrat"},{"ch":"L","size":18,"style":"Bold","w":60.4,"data":{"shapes":[{"ty":"gr","it":[{"ind":0,"ty":"sh","ix":1,"ks":{"a":0,"k":{"i":[[0,0],[0,0],[0,0],[0,0],[0,0],[0,0]],"o":[[0,0],[0,0],[0,0],[0,0],[0,0],[0,0]],"v":[[8.3,0],[59.6,0],[59.6,-13.2],[24.5,-13.2],[24.5,-70],[8.3,-70]],"c":true},"ix":2},"nm":"L","mn":"ADBE Vector Shape - Group","hd":false}],"nm":"L","np":3,"cix":2,"bm":0,"ix":1,"mn":"ADBE Vector Group","hd":false}]},"fFamily":"Montserrat"}]}